Metadata-Version: 2.1
Name: osu-cplayer
Version: 1.0.3
Summary: fast and featured command line osu! song player built on mpv
Home-page: https://github.com/eshrh/osu-cplayer
Author: Eshan Ramesh
Author-email: esrh@netc.eu
License: UNKNOWN
Platform: UNKNOWN
Classifier: Programming Language :: Python :: 3
Classifier: Operating System :: OS Independent
Requires-Python: >=3.6
